ip2location_toolkit/__init__.py
ip2location_toolkit/__main__.py
ip2location_toolkit/cli.py
ip2location_toolkit/db_codes.py
ip2location_toolkit/exceptions.py
ip2location_toolkit/validators.py
ip2location_toolkit/downloader/__init__.py
ip2location_toolkit/downloader/cli.py
ip2location_toolkit/downloader/download.py
ip2location_toolkit/downloader/update.py
ip2location_toolkit/selector/__init__.py
ip2location_toolkit/selector/cli.py
tests/__init__.py
tests/test_downloader.py
tests/test_update.py
tests/test_validators.py
tests/utils.py
ip2location_toolkit-0.1.0.dist-info/METADATA
ip2location_toolkit-0.1.0.dist-info/WHEEL
ip2location_toolkit-0.1.0.dist-info/entry_points.txt
ip2location_toolkit-0.1.0.dist-info/top_level.txt
ip2location_toolkit-0.1.0.dist-info/RECORD
