Metadata-Version: 2.1
Name: ip2location-toolkit
Version: 0.1.0
Summary: IP2Location Toolkit Allows User To Easily Download IP2Location and IP2Proxy Databases.
Home-page: https://github.com/Abdallah-Ragab/ip2location_toolkit
Author: Abdallah Ragab
Author-email: abdallahsamehragab1@gmail.com
Classifier: Development Status :: 3 - Alpha
Classifier: Intended Audience :: Developers
Classifier: License :: OSI Approved :: MIT License
Classifier: Programming Language :: Python :: 3
Classifier: Programming Language :: Python :: 3.6
Classifier: Programming Language :: Python :: 3.7
Classifier: Programming Language :: Python :: 3.8
Classifier: Programming Language :: Python :: 3.9
Classifier: Environment :: Console
Classifier: Operating System :: OS Independent
Classifier: Topic :: Internet :: Log Analysis
Classifier: Topic :: Internet :: WWW/HTTP
Classifier: Topic :: Software Development :: Libraries :: Python Modules
Classifier: Topic :: Utilities
Classifier: Topic :: System :: Networking
Requires: requests
Requires: tqdm
Requires: colorama
Requires-Python: >=3.0
